.gitignore
CHANGES.txt
LICENSE.txt
MANIFEST.in
README.txt
setup.py
dist/django-uocLTI-0.1.0.tar.gz
dist/django_uocLTI-0.1.0-py2.6.egg
django_uocLTI.egg-info/PKG-INFO
django_uocLTI.egg-info/SOURCES.txt
django_uocLTI.egg-info/dependency_links.txt
django_uocLTI.egg-info/not-zip-safe
django_uocLTI.egg-info/requires.txt
django_uocLTI.egg-info/top_level.txt
docs/README.txt
uocLTI/__init__.py
uocLTI/admin.py
uocLTI/models.py
uocLTI/tests.py
uocLTI/urls.py
uocLTI/utils.py
uocLTI/views.py
uocLTI/templates/base.html
uocLTI/templates/lti_role_denied.html