Metadata-Version: 1.0
Name: django-uocLTI
Version: 0.1.2
Summary: An IMS-LTI provider interface for django apps using the ims_lti_py library, created for use within the Universitat Obert de Catalunya UOC - nfinney 2013
Home-page: http://pypi.python.org/pypi/django-uocLTI
Author: Nathaniel Finney
Author-email: nfinney@uoc.edu
License: MIT licence, see LICENCE.txt
Platform: UNKNOWN
